pydynaa/__init__.py
pydynaa/version.py
pydynaa-0.0.1.dist-info/LICENSE
pydynaa-0.0.1.dist-info/METADATA
pydynaa-0.0.1.dist-info/WHEEL
pydynaa-0.0.1.dist-info/top_level.txt
pydynaa-0.0.1.dist-info/RECORD
