Metadata-Version: 2.1
Name: pydynaa
Version: 0.0.1
Summary: PyDynAA is a discrete event simulation engine
Home-page: https://netsquid.org
Author: TNO
Author-email: rob.knegjens@tno.nl
License: UNKNOWN
Project-URL: Website, https://netsquid.org
Keywords: simulator discrete event
Platform: UNKNOWN
Classifier: Development Status :: 3 - Alpha
Classifier: Programming Language :: Python :: 3
Classifier: Programming Language :: Python :: 3.5
Classifier: Programming Language :: Python :: 3.6
Classifier: Programming Language :: Python :: 3.7
Requires-Python: >=3.5
